[ {"en": "still", "cn": "还,仍然", "ipa": "[stɪl]"}, {"en": "programme", "cn": "(电视广播)节目", "ipa": "['prəʊgræm]"}, {"en": "lady", "cn": "女士,夫人", "ipa": "['leɪdi]"}, {"en": "life", "cn": "生活", "ipa": "[laɪf]"}, {"en": "different", "cn": "不同的", "ipa": "['dɪfrənt]"}, {"en": "ago", "cn": "以前", "ipa": "[əˈgəʊ]"}, {"en": "interviewer", "cn": "采访者", "ipa": "['ɪntəvju:ə(r)]"}, {"en": "enough", "cn": "足够的", "ipa": "[ɪˈnʌf]"}, {"en": "television", "cn": "电视机", "ipa": "['telɪvɪʒn]"}, {"en": "grandchildren", "cn": "(外)孙子;(外)孙女", "ipa": "[ɡ'ræntʃɪldrən]"}, {"en": "change", "cn": "改变,变化", "ipa": "[tʃeɪndʒ]"}, {"en": "night", "cn": "夜晚,夜间", "ipa": "[naɪt]"}, {"en": "work", "cn": "工作;劳动;干活儿", "ipa": "[wɜ:k]"}, {"en": "field", "cn": "田地", "ipa": "[fi:ld]"}, {"en": "fire", "cn": "火,炉火", "ipa": "['faɪə(r)]"}, {"en": "or", "cn": "(用于否定句中)也不,也没", "ipa": "[ɔ:(r)]"}, {"en": "radio", "cn": "收音机", "ipa": "['reɪdiəʊ]"}, {"en": "telephone", "cn": "电话", "ipa": "['telɪfəʊn]"}, {"en": "couldn't", "cn": "不能", "ipa": "['kʊdnt]"}, {"en": "write", "cn": "写", "ipa": "[raɪt]"}, {"en": "hope", "cn": "希望", "ipa": "[həʊp]"}, {"en": "learnt", "cn": "学习", "ipa": "[lɜ:nt]"}, {"en": "taught", "cn": "教,讲授", "ipa": "[tɔ:t]"}, {"en": "language", "cn": "语言", "ipa": "['læŋgwɪdʒ]"}, {"en": "wrote", "cn": "写", "ipa": "[rəʊt]"}, {"en": "dancer", "cn": "舞蹈演员", "ipa": "['dɑ:nsə(r)]"}, {"en": "foreign", "cn": "外国的", "ipa": "['fɒrən]"}, {"en": "studied", "cn": "学习", "ipa": "['stʌdid]"}, {"en": "hard", "cn": "努力地", "ipa": "[hɑ:d]"}, {"en": "hamburger", "cn": "汉堡包", "ipa": "['hæmbɜ:gə(r)]"}, {"en": "English", "cn": "英国(式)的", "ipa": "['ɪŋglɪʃ]"}, {"en": "breakfast", "cn": "早餐,早饭", "ipa": "['brekfəst]"}, {"en": "lunch", "cn": "午餐,午饭", "ipa": "[lʌntʃ]"}, {"en": "sandwich", "cn": "三明治", "ipa": "['sænwɪtʃ]"}, {"en": "fish and chips", "cn": "炸鱼加炸薯条", "ipa": "[fɪʃ] [tʃɪps]"}, {"en": "traditional", "cn": "传统的", "ipa": "[trəˈdɪʃənl]"}, {"en": "dish", "cn": "食品;菜肴", "ipa": "[dɪʃ]"}, {"en": "very much", "cn": "很,非常", "ipa": "['veri mʌtʃ]"}, {"en": "gave", "cn": "给", "ipa": "[geɪv]"}, {"en": "tonight", "cn": "今夜,今晚", "ipa": "[təˈnaɪt]"}, {"en": "library", "cn": "图书馆", "ipa": "['laɪbrəri]"}, {"en": "student", "cn": "学生", "ipa": "['stju:dnt]"}, {"en": "sent", "cn": "发送,寄", "ipa": "[sent]"}, {"en": "CD", "cn": "激光唱片,光盘", "ipa": "[si:ˈdi:]"}, {"en": "idea", "cn": "主意,想法", "ipa": "[aɪˈdɪə]"}, {"en": "put", "cn": "放,安放", "ipa": "[pʊt]"}, {"en": "shelf", "cn": "架子", "ipa": "[ʃelf]"}, {"en": "heavy", "cn": "重的,沉的", "ipa": "['hevi]"}, {"en": "dictionary", "cn": "词典;字典", "ipa": "['dɪkʃənri]"}, {"en": "card", "cn": "卡片", "ipa": "[kɑ:d]"}, {"en": "library card", "cn": "图书卡,借书证", "ipa": "[kɑ:d]"}, {"en": "ask", "cn": "邀请", "ipa": "[ɑ:sk]"}, {"en": "wrong", "cn": "错误的", "ipa": "[rɒŋ]"}, {"en": "dear", "cn": "哎呀", "ipa": "[dɪə(r)]"}, {"en": "information", "cn": "信息", "ipa": "[ˌɪnfəˈmeɪʃn]"}, {"en": "e-book", "cn": "电子书", "ipa": "[i:] [bi:k]"}, {"en": "project", "cn": "项目", "ipa": "['prɒdʒekt]"}, {"en": "guide", "cn": "介绍,指南,手册", "ipa": "[gaɪd]"}, {"en": "film", "cn": "电影", "ipa": "[fɪlm]"}, {"en": "as well", "cn": "又,还,也", "ipa": "[æz wel]"}, {"en": "way", "cn": "方法,方式", "ipa": "[weɪ]"}, {"en": "on", "cn": "关于", "ipa": "[ɒn]"}, {"en": "topic", "cn": "话题", "ipa": "['tɒpɪk]"}, {"en": "light", "cn": "轻的", "ipa": "[laɪt]"}, {"en": "hard", "cn": "困难的,费力的", "ipa": "[hɑ:d]"}, {"en": "broken", "cn": "坏了,破的", "ipa": "['brəʊkən]"}, {"en": "department store", "cn": "百货商店", "ipa": "[diˈpɑ:tmənt stɔ:]"}, {"en": "pocket", "cn": "口袋,兜", "ipa": "['pɒkɪt]"}, {"en": "umbrella", "cn": "雨伞", "ipa": "[ʌmˈbrelə]"}, {"en": "sales assistant", "cn": "售货员, 营业员", "ipa": "[seɪlz] [əˈsɪstənt]"}, {"en": "wheel", "cn": "轮子", "ipa": "[wi:l]"}, {"en": "easy", "cn": "容易的,不费力的", "ipa": "['i:zi]"}, {"en": "take", "cn": "选择要;选择购买", "ipa": "[teɪk]"}, {"en": "too", "cn": "太,过于", "ipa": "[tu:]"}, {"en": "try", "cn": "试,尝试", "ipa": "[traɪ]"}, {"en": "lovely", "cn": "美丽的,可爱的;令人愉快的", "ipa": "['lʌvli]"}, {"en": "moon", "cn": "月亮,月球", "ipa": "[mu:n]"}, {"en": "get", "cn": "到达", "ipa": "[get]"}, {"en": "west", "cn": "西,西部,西文;向西方", "ipa": "[west]"}, {"en": "parent", "cn": "母亲;父亲;家长", "ipa": "['peərənt]"}, {"en": "stay", "cn": "停留", "ipa": "[steɪ]"}, {"en": "July", "cn": "七月", "ipa": "[dʒuˈlaɪ]"}, {"en": "south", "cn": "南,南部,南方;向南方", "ipa": "[saʊθ]"}, {"en": "remember", "cn": "记得", "ipa": "[rɪˈmembə(r)]"}, {"en": "June", "cn": "六月", "ipa": "[dʒu:n]"}, {"en": "east", "cn": "东,东部,东方;向东方", "ipa": "[i:st]"}, {"en": "best", "cn": "最好的", "ipa": "[best]"}, {"en": "north", "cn": "北,北部,北方;向北方", "ipa": "[nɔ:θ]"}, {"en": "rest", "cn": "休息", "ipa": "[rest]"}, {"en": "have a rest", "cn": "休息一下", "ipa": "[hæv ə rest]"}, {"en": "rode", "cn": "骑", "ipa": "[rəʊd]"}, {"en": "evening", "cn": "傍晚,晚上", "ipa": "['i:vnɪŋ]"}, {"en": "late", "cn": "近日暮的;近深夜的;时间不早的", "ipa": "[leɪt]"}, {"en": "worker", "cn": "工人", "ipa": "['wɜ:kə(r)]"}, {"en": "factory", "cn": "制造厂;工厂", "ipa": "['fæktri]"}, {"en": "early", "cn": "早的", "ipa": "['ɜ:li]"}, {"en": "taxi", "cn": "出租车,计程车", "ipa": "['tæksi]"}, {"en": "quarter", "cn": "一刻钟", "ipa": "['kwɔ:tə(r)]"}, {"en": "to", "cn": "(距整点)差......", "ipa": "[tu]"}, {"en": "worry", "cn": "焦虑,担心", "ipa": "['wʌri]"}, {"en": "paper", "cn": "纸", "ipa": "['peɪpə(r)]"}, {"en": "Chinese", "cn": "中国人的", "ipa": "[ˌtʃaɪˈni:z]"}, {"en": "so", "cn": "如此,这样", "ipa": "[səʊ]"}, {"en": "word", "cn": "词,字", "ipa": "[wɜ:d]"}, {"en": "drew", "cn": "画", "ipa": "[dru:]"}, {"en": "cut", "cn": "剪,切,割", "ipa": "[kʌt]"}, {"en": "piece", "cn": "张,片,块", "ipa": "[pi:s]"}, {"en": "paint", "cn": "(用颜料)绘画,着色", "ipa": "[peɪnt]"}, {"en": "stick", "cn": "小木棍,小木条", "ipa": "[stɪk]"}, {"en": "tied", "cn": "扎上,系上", "ipa": "[taɪd]"}, {"en": "string", "cn": "线,绳子", "ipa": "[strɪŋ]"}, {"en": "laugh", "cn": "笑", "ipa": "[lɑ:f]"}, {"en": "wore", "cn": "穿", "ipa": "[wɔ:(r)]"}, {"en": "letter", "cn": "信,书信", "ipa": "['letə(r)]"}, {"en": "theatre", "cn": "剧院", "ipa": "['θiətə]"}, {"en": "women", "cn": "女性,妇女", "ipa": "['wɪmɪn]"}, {"en": "actor", "cn": "演员", "ipa": "['æktə(r)]"}, {"en": "told", "cn": "口述,讲(故事)", "ipa": "[təʊld]"}, {"en": "joke", "cn": "笑话", "ipa": "[dʒəʊk]"}, {"en": "after", "cn": "在......后", "ipa": "['ɑ:ftə(r)]"}, {"en": "show", "cn": "(尤指剧院的)演出,表演", "ipa": "[ʃəʊ]"}, {"en": "restaurant", "cn": "饭店,餐馆", "ipa": "['restrɒnt]"}, {"en": "ready", "cn": "准备好的", "ipa": "['redi]"}, {"en": "borrow", "cn": "借入,借来", "ipa": "['bɒrəʊ]"}, {"en": "read", "cn": "读", "ipa": "[ri:d]"}, {"en": "at all", "cn": "一点都", "ipa": "[æt ɔ:l]"}, {"en": "in", "cn": "在(将来一段时间)之后", "ipa": "[ɪn]"}, {"en": "another", "cn": "另一个", "ipa": "[əˈnʌðə(r)]"}, {"en": "history", "cn": "历史", "ipa": "['hɪstri]"}, {"en": "question", "cn": "问题", "ipa": "['kwestʃən]"}, {"en": "forget", "cn": "忘,忘记", "ipa": "[fəˈget]"}, {"en": "bring", "cn": "带来,拿来", "ipa": "[brɪŋ]"}, {"en": "soon", "cn": "不久,很快", "ipa": "[su:n]"}, {"en": "when", "cn": "在什么时候", "ipa": "[wen]"}, {"en": "end", "cn": "结束,终止", "ipa": "[end]"}, {"en": "nervous", "cn": "紧张的,情绪不安的", "ipa": "['nɜ:vəs]"}, {"en": "all right", "cn": "没事,没问题", "ipa": "[ɔ:l rait]"}, {"en": "airport", "cn": "机场", "ipa": "['eəpɔ:t]"}, {"en": "ticket", "cn": "票", "ipa": "['tɪkɪt]"}, {"en": "passport", "cn": "护照", "ipa": "['pɑ:spɔ:t]"}, {"en": "safe", "cn": "安全的,平安的", "ipa": "[seɪf]"}, {"en": "pet", "cn": "宠物", "ipa": "[pet]"}, {"en": "speak", "cn": "说,讲", "ipa": "[spi:k]"}, {"en": "building", "cn": "建筑物", "ipa": "['bɪldɪŋ]"}, {"en": "American", "cn": "美国的;美国人的;美国人", "ipa": "[əˈmerɪkən]"}, {"en": "find out", "cn": "发现,弄清", "ipa": "[faɪnd aʊt]"}, {"en": "more", "cn": "更多的(量),较多的(量)", "ipa": "[mɔ:(r)]"} ]